frida/__init__.py
frida/_frida.abi3.so
frida/core.py
frida/py.typed
frida/_frida/__init__.pyi
frida/_frida/py.typed
frida-17.6.2.dist-info/licenses/COPYING
frida-17.6.2.dist-info/METADATA
frida-17.6.2.dist-info/WHEEL
frida-17.6.2.dist-info/top_level.txt
frida-17.6.2.dist-info/RECORD
